[
  {
    "output": "fsutil   fsinfo  drives",
    "explanation": "Added extra spaces between command and arguments to test detection resilience against spacing variations."
  },
  {
    "output": "fsutil fsinfo drives",
    "explanation": "Original command with no mutation for baseline comparison."
  },
  {
    "output": "fsutil\" fsinfo drives",
    "explanation": "Inserted a quote after 'fsutil' to test detection resilience against quote insertion."
  },
  {
    "output": "fsutil fsinfo\" drives",
    "explanation": "Inserted a quote before 'drives' to test detection resilience against quote insertion."
  },
  {
    "output": "fsutil fsinfo^ drives",
    "explanation": "Inserted an escape character (^) before 'drives' to test detection resilience against escape character insertion."
  },
  {
    "output": "fsutil fsinfo ``drives",
    "explanation": "Used backticks as an alternative string representation for 'drives' to test detection resilience against recoding techniques."
  },
  {
    "output": "fsutil fsinfo `drives`",
    "explanation": "Wrapped 'drives' in backticks to test detection resilience against alternative string representation."
  },
  {
    "output": "fsutil fsinfo \"drives\"",
    "explanation": "Wrapped 'drives' in quotes to test detection resilience against quote insertion."
  },
  {
    "output": "fsutil fsinfo 'drives'",
    "explanation": "Wrapped 'drives' in single quotes to test detection resilience against quote insertion."
  },
  {
    "output": "fsutil fsinfo DRIVES",
    "explanation": "Used uppercase for 'drives' to test detection resilience against case variation."
  }
]
